yamlhparams/__init__.py
yamlhparams/package_info_utils.py
yamlhparams/version.py
yamlhparams/yaml_hparams.py
yamlhparams-0.2.0.dist-info/LICENSE.txt
yamlhparams-0.2.0.dist-info/METADATA
yamlhparams-0.2.0.dist-info/WHEEL
yamlhparams-0.2.0.dist-info/top_level.txt
yamlhparams-0.2.0.dist-info/RECORD
