Metadata-Version: 2.1
Name: yamlhparams
Version: 0.2.0
Summary: A small extension to the ruamel.yaml CommentedMap YAML parser intended for roundtrip loading, manipulation and saving of hyperparameters stored in YAML files while (optionally) performing basic version control against a separate Python package.
Home-page: https://github.com/perslev/yamlhparams
Author: Mathias Perslev
Author-email: map@di.ku.dk
License: UNKNOWN
Platform: UNKNOWN
Classifier: Programming Language :: Python :: 3.6
Classifier: Programming Language :: Python :: 3.7
Classifier: Programming Language :: Python :: 3.8
Classifier: Programming Language :: Python :: 3.9
Classifier: Programming Language :: Python :: 3.10
Classifier: Programming Language :: Python :: 3.11
License-File: LICENSE.txt
Requires-Dist: ruamel.yaml (>=0.17.21)
